<annotation>
	<folder>美工刀</folder>
	<filename>cutter_0120.jpg</filename>
	<path>C:\Users\schan\Downloads\dataset\美工刀\cutter_0120.jpg</path>
	<source>
		<database>Unknown</database>
	</source>
	<size>
		<width>750</width>
		<height>844</height>
		<depth>3</depth>
	</size>
	<segmented>0</segmented>
	<object>
		<name>cutter</name>
		<pose>Unspecified</pose>
		<truncated>0</truncated>
		<difficult>0</difficult>
		<bndbox>
			<xmin>81</xmin>
			<ymin>297</ymin>
			<xmax>719</xmax>
			<ymax>678</ymax>
		</bndbox>
	</object>
	<object>
		<name>cutter</name>
		<pose>Unspecified</pose>
		<truncated>0</truncated>
		<difficult>0</difficult>
		<bndbox>
			<xmin>36</xmin>
			<ymin>122</ymin>
			<xmax>675</xmax>
			<ymax>483</ymax>
		</bndbox>
	</object>
</annotation>
