<annotation>
	<folder>清潔劑</folder>
	<filename>cleaner_0081.png</filename>
	<path>C:\Users\schan\Downloads\dataset\清潔劑\cleaner_0081.png</path>
	<source>
		<database>Unknown</database>
	</source>
	<size>
		<width>800</width>
		<height>800</height>
		<depth>3</depth>
	</size>
	<segmented>0</segmented>
	<object>
		<name>cleaner</name>
		<pose>Unspecified</pose>
		<truncated>0</truncated>
		<difficult>0</difficult>
		<bndbox>
			<xmin>233</xmin>
			<ymin>154</ymin>
			<xmax>422</xmax>
			<ymax>758</ymax>
		</bndbox>
	</object>
	<object>
		<name>cleaner</name>
		<pose>Unspecified</pose>
		<truncated>0</truncated>
		<difficult>0</difficult>
		<bndbox>
			<xmin>34</xmin>
			<ymin>42</ymin>
			<xmax>220</xmax>
			<ymax>656</ymax>
		</bndbox>
	</object>
</annotation>
